fedgraph/__init__.py
fedgraph/data_process.py
fedgraph/federated_methods.py
fedgraph/gnn_models.py
fedgraph/he_context.pkl
fedgraph/monitor_class.py
fedgraph/server_class.py
fedgraph/train_func.py
fedgraph/trainer_class.py
fedgraph/utils_gc.py
fedgraph/utils_lp.py
fedgraph/utils_nc.py
fedgraph/version.py
fedgraph-0.2.5.dist-info/licenses/LICENSE
fedgraph-0.2.5.dist-info/METADATA
fedgraph-0.2.5.dist-info/WHEEL
fedgraph-0.2.5.dist-info/top_level.txt
fedgraph-0.2.5.dist-info/RECORD
