Metadata-Version: 2.4
Name: fedgraph
Version: 0.2.5
Summary: Federated Graph Learning
Home-page: https://github.com/FedGraph/fedgraph
Author: Yuhang Yao
Author-email: yuhangya@andrew.cmu.edu
Keywords: Graph Neural Networks,Federated Learning
Classifier: Programming Language :: Python :: 3
Classifier: Operating System :: OS Independent
Requires-Python: >=3.9
License-File: LICENSE
Requires-Dist: torch>=2.0.0
Requires-Dist: torch-scatter>=2.0.9
Requires-Dist: torch-sparse>=0.6.15
Requires-Dist: torch-cluster>=1.6.0
Requires-Dist: torch-spline-conv>=1.2.1
Requires-Dist: torch-geometric>=2.1.0.post1
Requires-Dist: omegaconf>=2.3.0
Requires-Dist: ray[default]>=2.6.3
Requires-Dist: PyYAML>=5.4.0
Requires-Dist: attridict
Requires-Dist: torchmetrics
Requires-Dist: setuptools
Requires-Dist: sphinx_rtd_theme
Requires-Dist: sphinxcontrib-bibtex
Requires-Dist: matplotlib
Requires-Dist: sphinx_gallery
Requires-Dist: tensorboard
Requires-Dist: dtaidistance
Requires-Dist: gdown
Requires-Dist: pandas
Requires-Dist: twine==5.0.0
Requires-Dist: scikit-learn
Requires-Dist: tenseal
Requires-Dist: huggingface_hub
Requires-Dist: ogb
Provides-Extra: dev
Requires-Dist: build; extra == "dev"
Requires-Dist: mypy; extra == "dev"
Requires-Dist: pre-commit; extra == "dev"
Requires-Dist: pytest; extra == "dev"
Dynamic: author
Dynamic: author-email
Dynamic: classifier
Dynamic: description
Dynamic: description-content-type
Dynamic: home-page
Dynamic: keywords
Dynamic: license-file
Dynamic: provides-extra
Dynamic: requires-dist
Dynamic: requires-python
Dynamic: summary
